{"title":"A Prayer","markdown":{"yaml":{"title":"A Prayer","date":"11-07-2020","categories":["poems"],"title-block-banner":false},"containsRefs":false,"markdown":"\n\n<div class = \"poem\">\n* I.\n* &nbsp;\n* In the riptide\n* &emsp; &emsp; of \n* &emsp; &emsp; this moment\n* may I act out of &emsp;\tgoodwill,\n* may I rediscover\n* the goodness &emsp; of others\n* &emsp; &emsp; made obfuscate\n* by timelines &emsp; &emsp; and party lines\n* &emsp; &emsp; and tighten the loosened thread\n* that ties us all\n* &emsp; together.\n* &nbsp;\n* II.\n* &nbsp;\n* The gift is knowing\n* what ails you\n* &nbsp;\n* the privilege is holding &emsp; &emsp;\tthat truth\n* without turning &emsp; away–\n* &nbsp;\n* what I fear most is not that you will hurt me\n* because in many ways you already have\n* but that I may never understand\t&emsp; why\n* &nbsp;\n* III. \n* &nbsp;\n* &emsp; &emsp; What I fear\n* most is not that &emsp;\tmy side is losing\n* but that we\n* &emsp; &emsp; &emsp; are lost.\n* &nbsp;\n* IV. \n* &nbsp;\n* May I summon &emsp;\tthe courage to speak\n* &emsp; &emsp; not out of &emsp; hate &emsp; or righteousness\n* not out of the pain\t&emsp; I’ve held for so long\n* both for myself &emsp;\tand for others,\n* &nbsp;\n* but with the soft palpitations of a heart\n* &emsp; &emsp; in search of redemption,\n* &emsp; with the hushed voice of a nation \n* &emsp; &emsp; dying for reconciliation.\n* &nbsp;\n* V. \n* &nbsp;\n* May our differences\n* sharpen our similarities.\n* &nbsp;\n* May I be bold enough\n* to witness your suffering\n* &nbsp;\n* and subsequently illuminate \n* the shape of my own.\n* &nbsp;\n* May we surf the edges with evermore grace\n* so that we can rise above the inevitable tide,\n* &nbsp;\n* swim ashore and dance \n* to the drumming of a fragile anthem\n* &nbsp;\n* celebrating\n* the birth of a nation.\n</div>"},"formats":{"html":{"execute":{"fig-width":7,"fig-height":5,"fig-format":"retina","fig-dpi":96,"error":false,"eval":true,"cache":null,"freeze":true,"echo":true,"output":true,"warning":true,"include":true,"keep-md":false,"keep-ipynb":false,"ipynb":null,"enabled":null,"daemon":null,"daemon-restart":false,"debug":false,"ipynb-filters":[],"engine":"markdown"},"render":{"keep-tex":false,"keep-yaml":false,"keep-source":false,"keep-hidden":false,"prefer-html":false,"output-divs":true,"output-ext":"html","fig-align":"default","fig-pos":null,"fig-env":null,"code-fold":"none","code-overflow":"scroll","code-link":false,"code-line-numbers":false,"code-tools":false,"tbl-colwidths":"auto","merge-includes":true,"latex-auto-mk":true,"latex-auto-install":true,"latex-clean":true,"latex-max-runs":10,"latex-makeindex":"makeindex","latex-makeindex-opts":[],"latex-tlmgr-opts":[],"latex-input-paths":[],"latex-output-dir":null,"link-external-icon":false,"link-external-newwindow":false},"pandoc":{"standalone":true,"wrap":"none","default-image-extension":"png","to":"html","css":["../../styles.css"],"output-file":"index.html"},"language":{},"metadata":{"lang":"en","fig-responsive":true,"quarto-version":"0.9.328","theme":"../../ember.scss","title-block-banner":false,"title":"A Prayer","date":"11-07-2020","categories":["poems"]},"extensions":{"book":{"multiFile":true}}}}}